test_yaoxing/__init__.py
yaoxing_ali-2.0.dist-info/METADATA
yaoxing_ali-2.0.dist-info/WHEEL
yaoxing_ali-2.0.dist-info/dependency_links.txt
yaoxing_ali-2.0.dist-info/top_level.txt
yaoxing_ali-2.0.dist-info/RECORD
