Metadata-Version: 2.1
Name: yaoxing-ali
Version: 2.0
Summary: test
Home-page: https://www.aliyun.com
Author: yaoxing
Author-email: yaoxing.lw@alibaba-inc.com
Requires-Dist: aiacc-training
